Workbook

Sheet Model
A1: s
B2: MULTIFAMILY UNDERWRITING MODEL
B3: Comprehensive Analysis with Creative Financing
B5: KEY DEAL METRICS | F5: SOURCES OF FUNDS | J5: USES OF FUNDS | N5: TRADITIONAL LOAN
B6: Property Name | D6: Riverside | F6: Source | G6: Amount | H6: % | J6: Use | K6: Amount | L6: % | N6: Loan Amount
B7: Total Units | D7: Model!D9 | F7: Traditional Loan | G7: =#REF! -> #REF! | H7: =IF($G$12=0,0,G7/$G$12) -> #REF! | J7: Purchase Price | K7: =D9 -> 1000000 | L7: =IF($K$12=0,0,K7/$K$12) -> #REF! | N7: Interest Rate
B8: Total SF | D8: 7948 | F8: Seller Financing | G8: =#REF! -> #REF! | H8: =IF($G$12=0,0,G8/$G$12) -> #REF! | J8: Closing Costs | K8: =#REF! -> #REF! | L8: =IF($K$12=0,0,K8/$K$12) -> #REF! | N8: Term (Months)
B9: Purchase Price | D9: 1000000 | F9: Seller Carryback | G9: =#REF! -> #REF! | H9: =IF($G$12=0,0,G9/$G$12) -> #REF! | J9: Due Diligence | K9: =#REF! -> #REF! | L9: =IF($K$12=0,0,K9/$K$12) -> #REF! | N9: Amortization (Months)
B10: Price Per SF | D10: =D9/D8 -> 125.81782 | F10: LP Equity | G10: =D104 -> #REF! | H10: =IF($G$12=0,0,G10/$G$12) -> #REF! | J10: Financing Costs | K10: =#REF! -> #REF! | L10: =IF($K$12=0,0,K10/$K$12) -> #REF! | N10: Monthly P&I | O10: =IF(O6=0,0,PMT(O7/12,O9,-O6)) -> 0
B11: Year 1 NOI | D11: =E73 -> #REF! | F11: GP Equity | G11: =D105 -> #REF! | H11: =IF($G$12=0,0,G11/$G$12) -> #REF! | J11: Operating Reserves | K11: =#REF! -> #REF! | L11: =IF($K$12=0,0,K11/$K$12) -> #REF! | N11: Annual Debt Service | O11: =O10*12 -> 0
B12: Going-In Cap Rate | D12: =IF(D9=0,0,D11/D9) -> #REF! | F12: Total Sources | G12: =SUM(G7:G11) -> #REF! | H12: =IF($G$12=0,0,G12/$G$12) -> #REF! | J12: Total Uses | K12: =SUM(K7:K11) -> #REF! | L12: =IF($K$12=0,0,K12/$K$12) -> #REF!
B13: Stabilized Cap Rate | D13: Model!D13 | N13: SELLER CARRYBACK / EQUITY PARTNER
B14: ═══════════════════════════════════════════════════════════════════════════════════════════════════════════════ | N14: Loan Amount
N15: Interest Rate
B16: UNIT MIX & RENT ROLL | N16: Term (Months)
B17: Unit # | C17: Type | D17: SF | E17: Status | F17: Market Rent | G17: In-Place Rent | H17: Loss to Lease | N17: Interest-Only (Y/N)
B18: 8 | C18: studio | D18: 300 | E18: rented | F18: 825 | G18: 822 | H18: =F18-G18 -> 3 | N18: Monthly Payment | O18: =IF(O17=1,O14*O15/12,IF(O14=0,0,PMT(O15/12,O16,-O14))) -> 0
B19: 8 | C19: 1bed/1bath | D19: 481 | F19: 950 | G19: 800 | H19: =F19-G19 -> 150 | N19: Annual Debt Service | O19: =O18*12 -> 0
B20: 2 | C20: 2b/2bath | D20: 853 | F20: 1100 | G20: 1025 | H20: =F20-G20 -> 75
H21: =F21-G21 -> 0 | N21: SELLER FINANCING (1ST POSITION)
H22: =F22-G22 -> 0 | N22: Loan Amount
H23: =F23-G23 -> 0 | N23: Interest Rate
H24: =F24-G24 -> 0 | N24: Term (Months)
H25: =F25-G25 -> 0 | N25: Amortization (Months)
H26: =F26-G26 -> 0 | N26: Interest-Only Period (Mo)
H27: =F27-G27 -> 0 | N27: Monthly P&I (after IO) | O27: =IF(O22=0,0,PMT(O23/12,O25,-O22)) -> 0
H28: =F28-G28 -> 0 | N28: Monthly IO Payment | O28: =O22*O23/12 -> 0
B29: TOTALS | D29: =SUM(D18:D28) -> 1634 | F29: =SUM(F18:F28) -> 2875 | G29: =SUM(G18:G28) -> 2647 | H29: =SUM(H18:H28) -> 228 | N29: Annual Debt Service | O29: =IF(O26>0,O28*12,O27*12) -> 0
B31: ═══════════════════════════════════════════════════════════════════════════════════════════════════════════════ | N31: BLENDED FINANCING SUMMARY
N32: Total Debt | O32: =O6+O14+O22 -> 0
B33: REVENUE PROJECTIONS | N33: Total Annual Debt Service | O33: =O11+O19+O29 -> 0
B34: Revenue Item | C34: $/Unit/Mo | D34: Annual | E34: Year 1 | F34: Year 2 | G34: Year 3 | H34: Year 4 | I34: Year 5 | J34: Year 6 | K34: Year 7 | L34: Year 8 | M34: Year 9 | N34: Blended Interest Rate | O34: =IF(O32=0,0,(O6*O7+O14*O15+O22*O23)/O32) -> 0
B35: Gross Potential Rent | C35: =D35/D7/12 -> #VALUE! | D35: =F29*12 -> 34500 | E35: =D35 -> 34500 | F35: =E35*(1+#REF!) -> #REF! | G35: =F35*(1+#REF!) -> #REF! | H35: =G35*(1+#REF!) -> #REF! | I35: =H35*(1+#REF!) -> #REF! | J35: =I35*(1+#REF!) -> #REF! | K35: =J35*(1+#REF!) -> #REF! | L35: =K35*(1+#REF!) -> #REF! | M35: =L35*(1+#REF!) -> #REF! | N35: Debt Yield | O35: =IF(O32=0,0,E73/O32) -> 0
B36: (Less) Vacancy | C36: =-C35*#REF! -> #VALUE! | D36: =-D35*#REF! -> #REF! | E36: =D36 -> #REF! | F36: =-F35*#REF! -> #REF! | G36: =-G35*#REF! -> #REF! | H36: =-H35*#REF! -> #REF! | I36: =-I35*#REF! -> #REF! | J36: =-J35*#REF! -> #REF! | K36: =-K35*#REF! -> #REF! | L36: =-L35*#REF! -> #REF! | M36: =-M35*#REF! -> #REF! | N36: LTV (% of Purchase) | O36: =IF(D9=0,0,O32/D9) -> 0
B37: (Less) Loss to Lease | C37: =D37/D7/12 -> #VALUE! | D37: =-H29*12 -> -2736 | E37: =D37 -> -2736 | F37: =E37*(1-0.1) -> -2462.4 | G37: =F37*(1-0.1) -> -2216.16 | H37: =G37*(1-0.1) -> -1994.544 | I37: =H37*(1-0.1) -> -1795.0896 | J37: =I37*(1-0.1) -> -1615.5806 | K37: =J37*(1-0.1) -> -1454.0226 | L37: =K37*(1-0.1) -> -1308.6203 | M37: =L37*(1-0.1) -> -1177.7583
B38: (Less) Concessions | C38: =-C35*#REF! -> #VALUE! | D38: =-D35*#REF! -> #REF! | E38: =D38 -> #REF! | F38: =-F35*#REF! -> #REF! | G38: =-G35*#REF! -> #REF! | H38: =-H35*#REF! -> #REF! | I38: =-I35*#REF! -> #REF! | J38: =-J35*#REF! -> #REF! | K38: =-K35*#REF! -> #REF! | L38: =-L35*#REF! -> #REF! | M38: =-M35*#REF! -> #REF!
B39: (Less) Bad Debt | C39: =-C35*#REF! -> #VALUE! | D39: =-D35*#REF! -> #REF! | E39: =D39 -> #REF! | F39: =-F35*#REF! -> #REF! | G39: =-G35*#REF! -> #REF! | H39: =-H35*#REF! -> #REF! | I39: =-I35*#REF! -> #REF! | J39: =-J35*#REF! -> #REF! | K39: =-K35*#REF! -> #REF! | L39: =-L35*#REF! -> #REF! | M39: =-M35*#REF! -> #REF!
B40: Net Rental Income | C40: =SUM(C35:C39) -> #VALUE! | D40: =SUM(D35:D39) -> #REF! | E40: =SUM(E35:E39) -> #REF! | F40: =SUM(F35:F39) -> #REF! | G40: =SUM(G35:G39) -> #REF! | H40: =SUM(H35:H39) -> #REF! | I40: =SUM(I35:I39) -> #REF! | J40: =SUM(J35:J39) -> #REF! | ... M40: =SUM(M35:M39) -> #REF!
B43: EFFECTIVE GROSS INCOME | D43: =D40 -> #REF! | E43: =E40 -> #REF! | F43: =F40 -> #REF! | G43: =G40 -> #REF! | H43: =H40 -> #REF! | I43: =I40 -> #REF! | J43: =J40 -> #REF! | K43: =K40 -> #REF! | ... N43: =N40
B45: ═══════════════════════════════════════════════════════════════════════════════════════════════════════════════
B47: OPERATING EXPENSES
B48: Expense Item | C48: $/Unit/Mo | D48: Annual | E48: Year 1 | F48: Year 2 | G48: Year 3 | H48: Year 4 | I48: Year 5 | J48: Year 6 | K48: Year 7 | L48: Year 8 | M48: Year 9 | N48: Year 10
B49: Real Estate Taxes | C49: 15536 | D49: =C49*12*$D$7 -> #VALUE! | E49: =D49 -> #VALUE! | F49: =E49*(1+#REF!) -> #VALUE! | G49: =F49*(1+#REF!) -> #VALUE! | H49: =G49*(1+#REF!) -> #VALUE! | I49: =H49*(1+#REF!) -> #VALUE! | J49: =I49*(1+#REF!) -> #VALUE! | K49: =J49*(1+#REF!) -> #VALUE! | L49: =K49*(1+#REF!) -> #VALUE! | M49: =L49*(1+#REF!) -> #VALUE! | N49: =M49*(1+#REF!) -> #VALUE!
B50: Property Insurance | C50: 1000 | D50: =C50*12*$D$7 -> #VALUE! | E50: =D50 -> #VALUE! | F50: =E50*(1+#REF!) -> #VALUE! | G50: =F50*(1+#REF!) -> #VALUE! | H50: =G50*(1+#REF!) -> #VALUE! | I50: =H50*(1+#REF!) -> #VALUE! | J50: =I50*(1+#REF!) -> #VALUE! | K50: =J50*(1+#REF!) -> #VALUE! | L50: =K50*(1+#REF!) -> #VALUE! | M50: =L50*(1+#REF!) -> #VALUE! | N50: =M50*(1+#REF!) -> #VALUE!
B51: Water/Sewer | D51: =C51*12*$D$7 -> #VALUE! | E51: =D51 -> #VALUE! | F51: =E51*(1+#REF!) -> #VALUE! | G51: =F51*(1+#REF!) -> #VALUE! | H51: =G51*(1+#REF!) -> #VALUE! | I51: =H51*(1+#REF!) -> #VALUE! | J51: =I51*(1+#REF!) -> #VALUE! | K51: =J51*(1+#REF!) -> #VALUE! | L51: =K51*(1+#REF!) -> #VALUE! | M51: =L51*(1+#REF!) -> #VALUE! | N51: =M51*(1+#REF!) -> #VALUE!
B52: Electric (Common) | D52: =C52*12*$D$7 -> #VALUE! | E52: =D52 -> #VALUE! | F52: =E52*(1+#REF!) -> #VALUE! | G52: =F52*(1+#REF!) -> #VALUE! | H52: =G52*(1+#REF!) -> #VALUE! | I52: =H52*(1+#REF!) -> #VALUE! | J52: =I52*(1+#REF!) -> #VALUE! | K52: =J52*(1+#REF!) -> #VALUE! | L52: =K52*(1+#REF!) -> #VALUE! | M52: =L52*(1+#REF!) -> #VALUE! | N52: =M52*(1+#REF!) -> #VALUE!
B53: Gas | D53: =C53*12*$D$7 -> #VALUE! | E53: =D53 -> #VALUE! | F53: =E53*(1+#REF!) -> #VALUE! | G53: =F53*(1+#REF!) -> #VALUE! | H53: =G53*(1+#REF!) -> #VALUE! | I53: =H53*(1+#REF!) -> #VALUE! | J53: =I53*(1+#REF!) -> #VALUE! | K53: =J53*(1+#REF!) -> #VALUE! | L53: =K53*(1+#REF!) -> #VALUE! | M53: =L53*(1+#REF!) -> #VALUE! | N53: =M53*(1+#REF!) -> #VALUE!
B54: Trash Removal | D54: =C54*12*$D$7 -> #VALUE! | E54: =D54 -> #VALUE! | F54: =E54*(1+#REF!) -> #VALUE! | G54: =F54*(1+#REF!) -> #VALUE! | H54: =G54*(1+#REF!) -> #VALUE! | I54: =H54*(1+#REF!) -> #VALUE! | J54: =I54*(1+#REF!) -> #VALUE! | K54: =J54*(1+#REF!) -> #VALUE! | L54: =K54*(1+#REF!) -> #VALUE! | M54: =L54*(1+#REF!) -> #VALUE! | N54: =M54*(1+#REF!) -> #VALUE!
B55: Repairs & Maintenance | D55: =C55*12*$D$7 -> #VALUE! | E55: =D55 -> #VALUE! | F55: =E55*(1+#REF!) -> #VALUE! | G55: =F55*(1+#REF!) -> #VALUE! | H55: =G55*(1+#REF!) -> #VALUE! | I55: =H55*(1+#REF!) -> #VALUE! | J55: =I55*(1+#REF!) -> #VALUE! | K55: =J55*(1+#REF!) -> #VALUE! | L55: =K55*(1+#REF!) -> #VALUE! | M55: =L55*(1+#REF!) -> #VALUE! | N55: =M55*(1+#REF!) -> #VALUE!
B56: Landscaping | D56: =C56*12*$D$7 -> #VALUE! | E56: Model!E117 | F56: =E56*(1+#REF!) -> #REF! | G56: =F56*(1+#REF!) -> #REF! | H56: =G56*(1+#REF!) -> #REF! | I56: =H56*(1+#REF!) -> #REF! | J56: =I56*(1+#REF!) -> #REF! | K56: =J56*(1+#REF!) -> #REF! | L56: =K56*(1+#REF!) -> #REF! | M56: =L56*(1+#REF!) -> #REF! | N56: =M56*(1+#REF!) -> #REF!
B57: Pest Control | D57: =C57*12*$D$7 -> #VALUE! | E57: =D57 -> #VALUE! | F57: =E57*(1+#REF!) -> #VALUE! | G57: =F57*(1+#REF!) -> #VALUE! | H57: =G57*(1+#REF!) -> #VALUE! | I57: =H57*(1+#REF!) -> #VALUE! | J57: =I57*(1+#REF!) -> #VALUE! | K57: =J57*(1+#REF!) -> #VALUE! | L57: =K57*(1+#REF!) -> #VALUE! | M57: =L57*(1+#REF!) -> #VALUE! | N57: =M57*(1+#REF!) -> #VALUE!
B58: Snow Removal | D58: =C58*12*$D$7 -> #VALUE! | E58: =D58 -> #VALUE! | F58: =E58*(1+#REF!) -> #VALUE! | G58: =F58*(1+#REF!) -> #VALUE! | H58: =G58*(1+#REF!) -> #VALUE! | I58: =H58*(1+#REF!) -> #VALUE! | J58: =I58*(1+#REF!) -> #VALUE! | K58: =J58*(1+#REF!) -> #VALUE! | L58: =K58*(1+#REF!) -> #VALUE! | M58: =L58*(1+#REF!) -> #VALUE! | N58: =M58*(1+#REF!) -> #VALUE!
B59: Unit Turnover | D59: =C59*12*$D$7 -> #VALUE! | E59: =D59 -> #VALUE! | F59: =E59*(1+#REF!) -> #VALUE! | G59: =F59*(1+#REF!) -> #VALUE! | H59: =G59*(1+#REF!) -> #VALUE! | I59: =H59*(1+#REF!) -> #VALUE! | J59: =I59*(1+#REF!) -> #VALUE! | K59: =J59*(1+#REF!) -> #VALUE! | L59: =K59*(1+#REF!) -> #VALUE! | M59: =L59*(1+#REF!) -> #VALUE! | N59: =M59*(1+#REF!) -> #VALUE!
B60: Management Fee | C60: =E43/12/$D$7*#REF! -> #REF! | D60: =C60*12*$D$7 -> #REF! | E60: =D60 -> #REF! | F60: =E60*(1+#REF!) -> #REF! | G60: =F60*(1+#REF!) -> #REF! | H60: =G60*(1+#REF!) -> #REF! | I60: =H60*(1+#REF!) -> #REF! | J60: =I60*(1+#REF!) -> #REF! | K60: =J60*(1+#REF!) -> #REF! | L60: =K60*(1+#REF!) -> #REF! | M60: =L60*(1+#REF!) -> #REF! | N60: =M60*(1+#REF!) -> #REF!
B61: On-Site Payroll | D61: =C61*12*$D$7 -> #VALUE! | E61: =D61 -> #VALUE! | F61: =E61*(1+#REF!) -> #VALUE! | G61: =F61*(1+#REF!) -> #VALUE! | H61: =G61*(1+#REF!) -> #VALUE! | I61: =H61*(1+#REF!) -> #VALUE! | J61: =I61*(1+#REF!) -> #VALUE! | K61: =J61*(1+#REF!) -> #VALUE! | L61: =K61*(1+#REF!) -> #VALUE! | M61: =L61*(1+#REF!) -> #VALUE! | N61: =M61*(1+#REF!) -> #VALUE!
B62: Marketing & Advertising | D62: =C62*12*$D$7 -> #VALUE! | E62: =D62 -> #VALUE! | F62: =E62*(1+#REF!) -> #VALUE! | G62: =F62*(1+#REF!) -> #VALUE! | H62: =G62*(1+#REF!) -> #VALUE! | I62: =H62*(1+#REF!) -> #VALUE! | J62: =I62*(1+#REF!) -> #VALUE! | K62: =J62*(1+#REF!) -> #VALUE! | L62: =K62*(1+#REF!) -> #VALUE! | M62: =L62*(1+#REF!) -> #VALUE! | N62: =M62*(1+#REF!) -> #VALUE!
B63: Legal & Professional | D63: =C63*12*$D$7 -> #VALUE! | E63: =D63 -> #VALUE! | F63: =E63*(1+#REF!) -> #VALUE! | G63: =F63*(1+#REF!) -> #VALUE! | H63: =G63*(1+#REF!) -> #VALUE! | I63: =H63*(1+#REF!) -> #VALUE! | J63: =I63*(1+#REF!) -> #VALUE! | K63: =J63*(1+#REF!) -> #VALUE! | L63: =K63*(1+#REF!) -> #VALUE! | M63: =L63*(1+#REF!) -> #VALUE! | N63: =M63*(1+#REF!) -> #VALUE!
B64: Accounting | D64: =C64*12*$D$7 -> #VALUE! | E64: =D64 -> #VALUE! | F64: =E64*(1+#REF!) -> #VALUE! | G64: =F64*(1+#REF!) -> #VALUE! | H64: =G64*(1+#REF!) -> #VALUE! | I64: =H64*(1+#REF!) -> #VALUE! | J64: =I64*(1+#REF!) -> #VALUE! | K64: =J64*(1+#REF!) -> #VALUE! | L64: =K64*(1+#REF!) -> #VALUE! | M64: =L64*(1+#REF!) -> #VALUE! | N64: =M64*(1+#REF!) -> #VALUE!
B65: Administrative | D65: =C65*12*$D$7 -> #VALUE! | E65: =D65 -> #VALUE! | F65: =E65*(1+#REF!) -> #VALUE! | G65: =F65*(1+#REF!) -> #VALUE! | H65: =G65*(1+#REF!) -> #VALUE! | I65: =H65*(1+#REF!) -> #VALUE! | J65: =I65*(1+#REF!) -> #VALUE! | K65: =J65*(1+#REF!) -> #VALUE! | L65: =K65*(1+#REF!) -> #VALUE! | M65: =L65*(1+#REF!) -> #VALUE! | N65: =M65*(1+#REF!) -> #VALUE!
B66: Security | D66: =C66*12*$D$7 -> #VALUE! | E66: =D66 -> #VALUE! | F66: =E66*(1+#REF!) -> #VALUE! | G66: =F66*(1+#REF!) -> #VALUE! | H66: =G66*(1+#REF!) -> #VALUE! | I66: =H66*(1+#REF!) -> #VALUE! | J66: =I66*(1+#REF!) -> #VALUE! | K66: =J66*(1+#REF!) -> #VALUE! | L66: =K66*(1+#REF!) -> #VALUE! | M66: =L66*(1+#REF!) -> #VALUE! | N66: =M66*(1+#REF!) -> #VALUE!
B67: Cable/Internet | D67: =C67*12*$D$7 -> #VALUE! | E67: =D67 -> #VALUE! | F67: =E67*(1+#REF!) -> #VALUE! | G67: =F67*(1+#REF!) -> #VALUE! | H67: =G67*(1+#REF!) -> #VALUE! | I67: =H67*(1+#REF!) -> #VALUE! | J67: =I67*(1+#REF!) -> #VALUE! | K67: =J67*(1+#REF!) -> #VALUE! | L67: =K67*(1+#REF!) -> #VALUE! | M67: =L67*(1+#REF!) -> #VALUE! | N67: =M67*(1+#REF!) -> #VALUE!
B68: Elevator Maintenance | D68: =C68*12*$D$7 -> #VALUE! | E68: =D68 -> #VALUE! | F68: =E68*(1+#REF!) -> #VALUE! | G68: =F68*(1+#REF!) -> #VALUE! | H68: =G68*(1+#REF!) -> #VALUE! | I68: =H68*(1+#REF!) -> #VALUE! | J68: =I68*(1+#REF!) -> #VALUE! | K68: =J68*(1+#REF!) -> #VALUE! | L68: =K68*(1+#REF!) -> #VALUE! | M68: =L68*(1+#REF!) -> #VALUE! | N68: =M68*(1+#REF!) -> #VALUE!
B69: Pool Maintenance | D69: =C69*12*$D$7 -> #VALUE! | E69: =D69 -> #VALUE! | F69: =E69*(1+#REF!) -> #VALUE! | G69: =F69*(1+#REF!) -> #VALUE! | H69: =G69*(1+#REF!) -> #VALUE! | I69: =H69*(1+#REF!) -> #VALUE! | J69: =I69*(1+#REF!) -> #VALUE! | K69: =J69*(1+#REF!) -> #VALUE! | L69: =K69*(1+#REF!) -> #VALUE! | M69: =L69*(1+#REF!) -> #VALUE! | N69: =M69*(1+#REF!) -> #VALUE!
B70: Replacement Reserves | C70: =#REF!/$D$7/12 -> #REF! | D70: =C70*12*$D$7 -> #REF! | E70: =D70 -> #REF! | F70: =E70*(1+0) -> #REF! | G70: =F70*(1+0) -> #REF! | H70: =G70*(1+0) -> #REF! | I70: =H70*(1+0) -> #REF! | J70: =I70*(1+0) -> #REF! | K70: =J70*(1+0) -> #REF! | L70: =K70*(1+0) -> #REF! | M70: =L70*(1+0) -> #REF! | N70: =M70*(1+0) -> #REF!
B71: TOTAL OPERATING EXPENSES | C71: =SUM(C49:C70) -> #REF! | D71: =SUM(D49:D70) -> #VALUE! | E71: =SUM(E49:E70) -> #VALUE! | F71: =SUM(F49:F70) -> #VALUE! | G71: =SUM(G49:G70) -> #VALUE! | H71: =SUM(H49:H70) -> #VALUE! | I71: =SUM(I49:I70) -> #VALUE! | J71: =SUM(J49:J70) -> #VALUE! | ... N71: =SUM(N49:N70) -> #VALUE!
B73: NET OPERATING INCOME (NOI) | D73: =D43-D71 -> #REF! | E73: =E43-E71 -> #REF! | F73: =F43-F71 -> #REF! | G73: =G43-G71 -> #REF! | H73: =H43-H71 -> #REF! | I73: =I43-I71 -> #REF! | J73: =J43-J71 -> #REF! | K73: =K43-K71 -> #REF! | ... N73: =N43-N71 -> #VALUE!
B75: Expense Ratio (% of EGI) | E75: =IF(E43=0,0,E71/E43) -> #REF! | F75: =IF(F43=0,0,F71/F43) -> #REF! | G75: =IF(G43=0,0,G71/G43) -> #REF! | H75: =IF(H43=0,0,H71/H43) -> #REF! | I75: =IF(I43=0,0,I71/I43) -> #REF! | J75: =IF(J43=0,0,J71/J43) -> #REF! | K75: =IF(K43=0,0,K71/K43) -> #REF! | L75: =IF(L43=0,0,L71/L43) -> #REF! | ... N75: =IF(N43=0,0,N71/N43) -> 0
B76: NOI Per Unit | E76: =IF($D$7=0,0,E73/$D$7) -> #REF! | F76: =IF($D$7=0,0,F73/$D$7) -> #REF! | G76: =IF($D$7=0,0,G73/$D$7) -> #REF! | H76: =IF($D$7=0,0,H73/$D$7) -> #REF! | I76: =IF($D$7=0,0,I73/$D$7) -> #REF! | J76: =IF($D$7=0,0,J73/$D$7) -> #REF! | K76: =IF($D$7=0,0,K73/$D$7) -> #REF! | L76: =IF($D$7=0,0,L73/$D$7) -> #REF! | ... N76: =IF($D$7=0,0,N73/$D$7) -> #VALUE!
B79: CASH FLOW PROJECTIONS
B80: Cash Flow Item | C80: Year 0 | D80: Year 1 | E80: Year 2 | F80: Year 3 | G80: Year 4
B81: Net Operating Income | D81: =E73 -> #REF! | E81: =F73 -> #REF! | F81: =G73 -> #REF! | G81: =H73 -> #REF!
B82: (-) Traditional Loan DS | D82: =-#REF! -> #REF! | E82: =-#REF! -> #REF! | F82: =-#REF! -> #REF! | G82: =-#REF! -> #REF!
B83: (-) Seller Financing DS | D83: =-#REF! -> #REF! | E83: =-#REF! -> #REF! | F83: =-#REF! -> #REF! | G83: =-#REF! -> #REF!
B84: (-) Seller Carryback DS | D84: =-#REF! -> #REF! | E84: =-#REF! -> #REF! | F84: =-#REF! -> #REF! | G84: =-#REF! -> #REF!
B85: Total Debt Service | D85: =SUM(D82:D84) -> #REF! | E85: =SUM(E82:E84) -> #REF! | F85: =SUM(F82:F84) -> #REF! | G85: =SUM(G82:G84) -> #REF!
B86: (-) CapEx/Reserves | D86: =-#REF!-#REF! -> #REF! | E86: =-#REF! -> #REF! | F86: =-#REF! -> #REF! | G86: =-#REF! -> #REF!
B87: Before-Tax Cash Flow | D87: =D81+D85+D86 -> #REF! | E87: =E81+E85+E86 -> #REF! | F87: =F81+F85+F86 -> #REF! | G87: =G81+G85+G86 -> #REF!
B89: DSCR (NOI/Debt Service) | D89: =IF(D85=0,0,D81/-D85) -> #REF! | E89: =IF(E85=0,0,E81/-E85) -> #REF! | F89: =IF(F85=0,0,F81/-F85) -> #REF! | G89: =IF(G85=0,0,G81/-G85) -> #REF!
B90: Cash-on-Cash Return | D90: =IF(D105=0,0,D87/D105) -> #REF! | E90: =IF(E105=0,0,E87/E105) -> 0 | F90: =IF(F105=0,0,F87/F105) -> 0 | G90: =IF(G105=0,0,G87/G105) -> 0
B92: SALE / REVERSION ANALYSIS
B93: Exit Cap Rate Applied
B94: Forward NOI (Next Year)
B95: Gross Sale Price | H95: Year 5 | I95: Year 6 | J95: Year 7 | K95: Year 8 | L95: Year 9 | M95: Year 10
B96: (-) Selling Costs | H96: =I73 -> #REF! | I96: =J73 -> #REF! | J96: =K73 -> #REF! | K96: =L73 -> #REF! | L96: =M73 -> #REF! | M96: =N73 -> #VALUE!
B97: (-) Loan Payoffs | H97: =-#REF! -> #REF! | I97: =-#REF! -> #REF! | J97: =-#REF! -> #REF! | K97: =-#REF! -> #REF! | L97: =-#REF! -> #REF! | M97: =-#REF! -> #REF!
B98: Net Sale Proceeds | H98: =-#REF! -> #REF! | I98: =-#REF! -> #REF! | J98: =-#REF! -> #REF! | K98: =-#REF! -> #REF! | L98: =-#REF! -> #REF! | M98: =-#REF! -> #REF!
B100: EQUITY INVESTMENT
B101: Total Acquisition Cost | D101: =D9+#REF!+#REF!+#REF!+#REF!+#REF! -> #REF! | H101: =SUM(H97:H98) -> #REF! | I101: =SUM(I97:I98) -> #REF! | J101: =SUM(J97:J98) -> #REF! | K101: =SUM(K97:K98) -> #REF! | L101: =SUM(L97:L98) -> #REF! | M101: =SUM(M97:M98) -> #REF!
B102: (-) Total Debt | D102: =-#REF! -> #REF! | H102: =-#REF! -> #REF! | I102: =-#REF! -> #REF! | J102: =-#REF! -> #REF! | K102: =-#REF! -> #REF! | L102: =-#REF! -> #REF! | M102: =-#REF! -> #REF!
B103: Required Equity | D103: =D101+D102 -> #REF! | H103: =H96+H101+H102 -> #REF! | I103: =I96+I101+I102 -> #REF! | J103: =J96+J101+J102 -> #REF! | K103: =K96+K101+K102 -> #REF! | L103: =L96+L101+L102 -> #REF! | M103: =M96+M101+M102 -> #VALUE!
B104: LP Equity (90%) | D104: =D103*0.9 -> #REF!
B105: GP Equity (10%) | D105: =D103*0.1 -> #REF! | H105: =IF(H101=0,0,H96/-H101) -> #REF! | I105: =IF(I101=0,0,I96/-I101) -> #REF! | J105: =IF(J101=0,0,J96/-J101) -> #REF! | K105: =IF(K101=0,0,K96/-K101) -> #REF! | L105: =IF(L101=0,0,L96/-L101) -> #REF! | M105: =IF(M101=0,0,M96/-M101) -> #REF!
H106: =IF(#REF!=0,0,H103/#REF!) -> #REF! | I106: =IF(#REF!=0,0,I103/#REF!) -> #REF! | J106: =IF(#REF!=0,0,J103/#REF!) -> #REF! | K106: =IF(#REF!=0,0,K103/#REF!) -> #REF! | L106: =IF(#REF!=0,0,L103/#REF!) -> #REF! | M106: =IF(#REF!=0,0,M103/#REF!) -> #REF!
B107: IRR CASH FLOWS
B108: Initial Investment | C108: =-D103 -> #REF!
B109: Operating Cash Flow | D109: =D87 -> #REF! | E109: =E87 -> #REF! | F109: =F87 -> #REF! | G109: =G87 -> #REF! | H109: =#REF! -> #REF! | M109: =#REF! -> #REF!
B110: Sale Proceeds (5-Yr) | H110: =I96 -> #REF! | M110: =M96*(1+#REF!) -> #VALUE!
B111: Sale Proceeds (10-Yr) | H111: =IF(H109=0,0,H110/H109) -> #REF! | M111: =IF(M109=0,0,M110/M109) -> #REF!
B112: Total CF (5-Yr Exit) | C112: =C108 -> #REF! | D112: =D109 -> #REF! | E112: =E109 -> #REF! | F112: =F109 -> #REF! | G112: =G109 -> #REF! | H112: =-H111*#REF! -> #REF! | M112: =-M111*#REF! -> #REF!
B113: Total CF (10-Yr Exit) | C113: =C108 -> #REF! | D113: =D109 -> #REF! | E113: =E109 -> #REF! | F113: =F109 -> #REF! | G113: =G109 -> #REF! | H113: =-#REF! -> #REF! | M113: =-#REF! -> #REF!
...

Sheet RUBS
B2: RATIO UTILITY BILLING SYSTEM (RUBS)
B3: Utility Cost Allocation & Recovery Model
B5: CONFIGURATION | F5: INSTRUCTIONS
B6: Property References | F6: 1. Enter monthly utility costs in the Utility Cost Inputs section (blue cells)
B7: Total Units | C7: =Model!D7 -> Model!D9 | F7: 2. Select allocation method for each utility: SF, Units, or Occupancy
B8: Total SF | C8: =Model!D8 -> 7948 | F8: 3. Enter occupant count per unit in the Unit Detail table (blue cells)
F9: 4. Adjust admin fee settings as needed ($/unit or % markup)
B10: Admin Fee Settings | F10: 5. Review Summary Output for cost recovery analysis
B11: Admin Fee ($/unit/mo) | C11: 5
B12: Admin Fee (% markup) | C12: 0.05 | F12: COLOR LEGEND:
B13: Use Fee Method | C13: $/unit | D13: ($/unit or % markup) | F13: Blue text = User input
B14: Target Recovery % | C14: 1 | F14: Green text = Cross-sheet reference
F15: Black text = Calculated formula
B16: UTILITY COST INPUTS
B17: Utility | C17: Monthly Cost | D17: Annual Cost | E17: Allocation Method | F17: Methods: SF, Units, Occupancy
B18: Water/Sewer | C18: 0 | D18: =C18*12 -> 0 | E18: Units
B19: Electric (Common) | C19: 0 | D19: =C19*12 -> 0 | E19: SF
B20: Gas | C20: 0 | D20: =C20*12 -> 0 | E20: Units
B21: Trash | C21: 0 | D21: =C21*12 -> 0 | E21: Units
B22: Other | C22: 0 | D22: =C22*12 -> 0 | E22: SF
B23: TOTAL | C23: =SUM(C18:C22) -> 0 | D23: =SUM(D18:D22) -> 0
B25: SUMMARY OUTPUT
B26: Cost Recovery | C26: Monthly | D26: Annual
B27: Total Utility Costs | C27: =C23 -> 0 | D27: =D23 -> 0
B28: Total Allocated to Units | C28: =IFERROR(SUM(K44:K54),0) -> 0 | D28: =IFERROR(SUM(L44:L54),0) -> 0
B29: Admin Fees Collected | C29: =IFERROR(IF(C13="$/unit",C11*C7,C12*C28),0) -> 0 | D29: =C29*12 -> 0
B30: Gross Revenue from RUBS | C30: =C28+C29 -> 0 | D30: =D28+D29 -> 0
B31: Net Recovery | C31: =C30-C27 -> 0 | D31: =D30-D27 -> 0
B33: Recovery Metrics
B34: Recovery % Achieved | C34: =IFERROR(C31/C27,0) -> 0 | D34: =IFERROR(D31/D27,0) -> 0
B35: Target Recovery % | C35: =C14 -> 1 | D35: =C14 -> 1
B36: Variance vs Target | C36: =C34-C35 -> -1 | D36: =D34-D35 -> -1
B38: Cost per Unit (Monthly) | C38: =IFERROR(C27/C7,0) -> 0
B39: Cost per SF (Monthly) | C39: =IFERROR(C27/C8,0) -> 0
B40: Revenue per Unit (Monthly) | C40: =IFERROR(C31/C7,0) -> 0
B42: UNIT-LEVEL DETAIL
B43: Unit # | C43: Type | D43: SF | E43: Occupants | F43: Water/Sewer | G43: Electric | H43: Gas | I43: Trash | J43: Other | K43: Total Monthly | L43: Total Annual
B44: =Model!B18 -> 8 | C44: =Model!C18 -> studio | D44: =Model!D18 -> 300 | E44: 2 | F44: =IFERROR(IF($E$18="SF",$C$18*D44/$C$8,IF($E$18="Units",$C$18/$C$7,IF($E$18="Occupancy",$C$18*E44/SUM($E$44:$E$54),$C$18/$C$7))),0) -> 0 | G44: =IFERROR(IF($E$19="SF",$C$19*D44/$C$8,IF($E$19="Units",$C$19/$C$7,IF($E$19="Occupancy",$C$19*E44/SUM($E$44:$E$54),$C$19/$C$7))),0) -> 0 | H44: =IFERROR(IF($E$20="SF",$C$20*D44/$C$8,IF($E$20="Units",$C$20/$C$7,IF($E$20="Occupancy",$C$20*E44/SUM($E$44:$E$54),$C$20/$C$7))),0) -> 0 | I44: =IFERROR(IF($E$21="SF",$C$21*D44/$C$8,IF($E$21="Units",$C$21/$C$7,IF($E$21="Occupancy",$C$21*E44/SUM($E$44:$E$54),$C$21/$C$7))),0) -> 0 | J44: =IFERROR(IF($E$22="SF",$C$22*D44/$C$8,IF($E$22="Units",$C$22/$C$7,IF($E$22="Occupancy",$C$22*E44/SUM($E$44:$E$54),$C$22/$C$7))),0) -> 0 | K44: =SUM(F44:J44) -> 0 | L44: =K44*12 -> 0
B45: =Model!B19 -> 8 | C45: =Model!C19 -> 1bed/1bath | D45: =Model!D19 -> 481 | E45: 2 | F45: =IFERROR(IF($E$18="SF",$C$18*D45/$C$8,IF($E$18="Units",$C$18/$C$7,IF($E$18="Occupancy",$C$18*E45/SUM($E$44:$E$54),$C$18/$C$7))),0) -> 0 | G45: =IFERROR(IF($E$19="SF",$C$19*D45/$C$8,IF($E$19="Units",$C$19/$C$7,IF($E$19="Occupancy",$C$19*E45/SUM($E$44:$E$54),$C$19/$C$7))),0) -> 0 | H45: =IFERROR(IF($E$20="SF",$C$20*D45/$C$8,IF($E$20="Units",$C$20/$C$7,IF($E$20="Occupancy",$C$20*E45/SUM($E$44:$E$54),$C$20/$C$7))),0) -> 0 | I45: =IFERROR(IF($E$21="SF",$C$21*D45/$C$8,IF($E$21="Units",$C$21/$C$7,IF($E$21="Occupancy",$C$21*E45/SUM($E$44:$E$54),$C$21/$C$7))),0) -> 0 | J45: =IFERROR(IF($E$22="SF",$C$22*D45/$C$8,IF($E$22="Units",$C$22/$C$7,IF($E$22="Occupancy",$C$22*E45/SUM($E$44:$E$54),$C$22/$C$7))),0) -> 0 | K45: =SUM(F45:J45) -> 0 | L45: =K45*12 -> 0
B46: =Model!B20 -> 2 | C46: =Model!C20 -> 2b/2bath | D46: =Model!D20 -> 853 | E46: 2 | F46: =IFERROR(IF($E$18="SF",$C$18*D46/$C$8,IF($E$18="Units",$C$18/$C$7,IF($E$18="Occupancy",$C$18*E46/SUM($E$44:$E$54),$C$18/$C$7))),0) -> 0 | G46: =IFERROR(IF($E$19="SF",$C$19*D46/$C$8,IF($E$19="Units",$C$19/$C$7,IF($E$19="Occupancy",$C$19*E46/SUM($E$44:$E$54),$C$19/$C$7))),0) -> 0 | H46: =IFERROR(IF($E$20="SF",$C$20*D46/$C$8,IF($E$20="Units",$C$20/$C$7,IF($E$20="Occupancy",$C$20*E46/SUM($E$44:$E$54),$C$20/$C$7))),0) -> 0 | I46: =IFERROR(IF($E$21="SF",$C$21*D46/$C$8,IF($E$21="Units",$C$21/$C$7,IF($E$21="Occupancy",$C$21*E46/SUM($E$44:$E$54),$C$21/$C$7))),0) -> 0 | J46: =IFERROR(IF($E$22="SF",$C$22*D46/$C$8,IF($E$22="Units",$C$22/$C$7,IF($E$22="Occupancy",$C$22*E46/SUM($E$44:$E$54),$C$22/$C$7))),0) -> 0 | K46: =SUM(F46:J46) -> 0 | L46: =K46*12 -> 0
B47: =Model!B21 | C47: =Model!C21 | D47: =Model!D21 | E47: 2 | F47: =IFERROR(IF($E$18="SF",$C$18*D47/$C$8,IF($E$18="Units",$C$18/$C$7,IF($E$18="Occupancy",$C$18*E47/SUM($E$44:$E$54),$C$18/$C$7))),0) -> 0 | G47: =IFERROR(IF($E$19="SF",$C$19*D47/$C$8,IF($E$19="Units",$C$19/$C$7,IF($E$19="Occupancy",$C$19*E47/SUM($E$44:$E$54),$C$19/$C$7))),0) -> 0 | H47: =IFERROR(IF($E$20="SF",$C$20*D47/$C$8,IF($E$20="Units",$C$20/$C$7,IF($E$20="Occupancy",$C$20*E47/SUM($E$44:$E$54),$C$20/$C$7))),0) -> 0 | I47: =IFERROR(IF($E$21="SF",$C$21*D47/$C$8,IF($E$21="Units",$C$21/$C$7,IF($E$21="Occupancy",$C$21*E47/SUM($E$44:$E$54),$C$21/$C$7))),0) -> 0 | J47: =IFERROR(IF($E$22="SF",$C$22*D47/$C$8,IF($E$22="Units",$C$22/$C$7,IF($E$22="Occupancy",$C$22*E47/SUM($E$44:$E$54),$C$22/$C$7))),0) -> 0 | K47: =SUM(F47:J47) -> 0 | L47: =K47*12 -> 0
B48: =Model!B22 | C48: =Model!C22 | D48: =Model!D22 | E48: 2 | F48: =IFERROR(IF($E$18="SF",$C$18*D48/$C$8,IF($E$18="Units",$C$18/$C$7,IF($E$18="Occupancy",$C$18*E48/SUM($E$44:$E$54),$C$18/$C$7))),0) -> 0 | G48: =IFERROR(IF($E$19="SF",$C$19*D48/$C$8,IF($E$19="Units",$C$19/$C$7,IF($E$19="Occupancy",$C$19*E48/SUM($E$44:$E$54),$C$19/$C$7))),0) -> 0 | H48: =IFERROR(IF($E$20="SF",$C$20*D48/$C$8,IF($E$20="Units",$C$20/$C$7,IF($E$20="Occupancy",$C$20*E48/SUM($E$44:$E$54),$C$20/$C$7))),0) -> 0 | I48: =IFERROR(IF($E$21="SF",$C$21*D48/$C$8,IF($E$21="Units",$C$21/$C$7,IF($E$21="Occupancy",$C$21*E48/SUM($E$44:$E$54),$C$21/$C$7))),0) -> 0 | J48: =IFERROR(IF($E$22="SF",$C$22*D48/$C$8,IF($E$22="Units",$C$22/$C$7,IF($E$22="Occupancy",$C$22*E48/SUM($E$44:$E$54),$C$22/$C$7))),0) -> 0 | K48: =SUM(F48:J48) -> 0 | L48: =K48*12 -> 0
B49: =Model!B23 | C49: =Model!C23 | D49: =Model!D23 | E49: 2 | F49: =IFERROR(IF($E$18="SF",$C$18*D49/$C$8,IF($E$18="Units",$C$18/$C$7,IF($E$18="Occupancy",$C$18*E49/SUM($E$44:$E$54),$C$18/$C$7))),0) -> 0 | G49: =IFERROR(IF($E$19="SF",$C$19*D49/$C$8,IF($E$19="Units",$C$19/$C$7,IF($E$19="Occupancy",$C$19*E49/SUM($E$44:$E$54),$C$19/$C$7))),0) -> 0 | H49: =IFERROR(IF($E$20="SF",$C$20*D49/$C$8,IF($E$20="Units",$C$20/$C$7,IF($E$20="Occupancy",$C$20*E49/SUM($E$44:$E$54),$C$20/$C$7))),0) -> 0 | I49: =IFERROR(IF($E$21="SF",$C$21*D49/$C$8,IF($E$21="Units",$C$21/$C$7,IF($E$21="Occupancy",$C$21*E49/SUM($E$44:$E$54),$C$21/$C$7))),0) -> 0 | J49: =IFERROR(IF($E$22="SF",$C$22*D49/$C$8,IF($E$22="Units",$C$22/$C$7,IF($E$22="Occupancy",$C$22*E49/SUM($E$44:$E$54),$C$22/$C$7))),0) -> 0 | K49: =SUM(F49:J49) -> 0 | L49: =K49*12 -> 0
B50: =Model!B24 | C50: =Model!C24 | D50: =Model!D24 | E50: 2 | F50: =IFERROR(IF($E$18="SF",$C$18*D50/$C$8,IF($E$18="Units",$C$18/$C$7,IF($E$18="Occupancy",$C$18*E50/SUM($E$44:$E$54),$C$18/$C$7))),0) -> 0 | G50: =IFERROR(IF($E$19="SF",$C$19*D50/$C$8,IF($E$19="Units",$C$19/$C$7,IF($E$19="Occupancy",$C$19*E50/SUM($E$44:$E$54),$C$19/$C$7))),0) -> 0 | H50: =IFERROR(IF($E$20="SF",$C$20*D50/$C$8,IF($E$20="Units",$C$20/$C$7,IF($E$20="Occupancy",$C$20*E50/SUM($E$44:$E$54),$C$20/$C$7))),0) -> 0 | I50: =IFERROR(IF($E$21="SF",$C$21*D50/$C$8,IF($E$21="Units",$C$21/$C$7,IF($E$21="Occupancy",$C$21*E50/SUM($E$44:$E$54),$C$21/$C$7))),0) -> 0 | J50: =IFERROR(IF($E$22="SF",$C$22*D50/$C$8,IF($E$22="Units",$C$22/$C$7,IF($E$22="Occupancy",$C$22*E50/SUM($E$44:$E$54),$C$22/$C$7))),0) -> 0 | K50: =SUM(F50:J50) -> 0 | L50: =K50*12 -> 0
B51: =Model!B25 | C51: =Model!C25 | D51: =Model!D25 | E51: 2 | F51: =IFERROR(IF($E$18="SF",$C$18*D51/$C$8,IF($E$18="Units",$C$18/$C$7,IF($E$18="Occupancy",$C$18*E51/SUM($E$44:$E$54),$C$18/$C$7))),0) -> 0 | G51: =IFERROR(IF($E$19="SF",$C$19*D51/$C$8,IF($E$19="Units",$C$19/$C$7,IF($E$19="Occupancy",$C$19*E51/SUM($E$44:$E$54),$C$19/$C$7))),0) -> 0 | H51: =IFERROR(IF($E$20="SF",$C$20*D51/$C$8,IF($E$20="Units",$C$20/$C$7,IF($E$20="Occupancy",$C$20*E51/SUM($E$44:$E$54),$C$20/$C$7))),0) -> 0 | I51: =IFERROR(IF($E$21="SF",$C$21*D51/$C$8,IF($E$21="Units",$C$21/$C$7,IF($E$21="Occupancy",$C$21*E51/SUM($E$44:$E$54),$C$21/$C$7))),0) -> 0 | J51: =IFERROR(IF($E$22="SF",$C$22*D51/$C$8,IF($E$22="Units",$C$22/$C$7,IF($E$22="Occupancy",$C$22*E51/SUM($E$44:$E$54),$C$22/$C$7))),0) -> 0 | K51: =SUM(F51:J51) -> 0 | L51: =K51*12 -> 0
B52: =Model!B26 | C52: =Model!C26 | D52: =Model!D26 | E52: 2 | F52: =IFERROR(IF($E$18="SF",$C$18*D52/$C$8,IF($E$18="Units",$C$18/$C$7,IF($E$18="Occupancy",$C$18*E52/SUM($E$44:$E$54),$C$18/$C$7))),0) -> 0 | G52: =IFERROR(IF($E$19="SF",$C$19*D52/$C$8,IF($E$19="Units",$C$19/$C$7,IF($E$19="Occupancy",$C$19*E52/SUM($E$44:$E$54),$C$19/$C$7))),0) -> 0 | H52: =IFERROR(IF($E$20="SF",$C$20*D52/$C$8,IF($E$20="Units",$C$20/$C$7,IF($E$20="Occupancy",$C$20*E52/SUM($E$44:$E$54),$C$20/$C$7))),0) -> 0 | I52: =IFERROR(IF($E$21="SF",$C$21*D52/$C$8,IF($E$21="Units",$C$21/$C$7,IF($E$21="Occupancy",$C$21*E52/SUM($E$44:$E$54),$C$21/$C$7))),0) -> 0 | J52: =IFERROR(IF($E$22="SF",$C$22*D52/$C$8,IF($E$22="Units",$C$22/$C$7,IF($E$22="Occupancy",$C$22*E52/SUM($E$44:$E$54),$C$22/$C$7))),0) -> 0 | K52: =SUM(F52:J52) -> 0 | L52: =K52*12 -> 0
B53: =Model!B27 | C53: =Model!C27 | D53: =Model!D27 | E53: 2 | F53: =IFERROR(IF($E$18="SF",$C$18*D53/$C$8,IF($E$18="Units",$C$18/$C$7,IF($E$18="Occupancy",$C$18*E53/SUM($E$44:$E$54),$C$18/$C$7))),0) -> 0 | G53: =IFERROR(IF($E$19="SF",$C$19*D53/$C$8,IF($E$19="Units",$C$19/$C$7,IF($E$19="Occupancy",$C$19*E53/SUM($E$44:$E$54),$C$19/$C$7))),0) -> 0 | H53: =IFERROR(IF($E$20="SF",$C$20*D53/$C$8,IF($E$20="Units",$C$20/$C$7,IF($E$20="Occupancy",$C$20*E53/SUM($E$44:$E$54),$C$20/$C$7))),0) -> 0 | I53: =IFERROR(IF($E$21="SF",$C$21*D53/$C$8,IF($E$21="Units",$C$21/$C$7,IF($E$21="Occupancy",$C$21*E53/SUM($E$44:$E$54),$C$21/$C$7))),0) -> 0 | J53: =IFERROR(IF($E$22="SF",$C$22*D53/$C$8,IF($E$22="Units",$C$22/$C$7,IF($E$22="Occupancy",$C$22*E53/SUM($E$44:$E$54),$C$22/$C$7))),0) -> 0 | K53: =SUM(F53:J53) -> 0 | L53: =K53*12 -> 0
B54: =Model!B28 | C54: =Model!C28 | D54: =Model!D28 | E54: 2 | F54: =IFERROR(IF($E$18="SF",$C$18*D54/$C$8,IF($E$18="Units",$C$18/$C$7,IF($E$18="Occupancy",$C$18*E54/SUM($E$44:$E$54),$C$18/$C$7))),0) -> 0 | G54: =IFERROR(IF($E$19="SF",$C$19*D54/$C$8,IF($E$19="Units",$C$19/$C$7,IF($E$19="Occupancy",$C$19*E54/SUM($E$44:$E$54),$C$19/$C$7))),0) -> 0 | H54: =IFERROR(IF($E$20="SF",$C$20*D54/$C$8,IF($E$20="Units",$C$20/$C$7,IF($E$20="Occupancy",$C$20*E54/SUM($E$44:$E$54),$C$20/$C$7))),0) -> 0 | I54: =IFERROR(IF($E$21="SF",$C$21*D54/$C$8,IF($E$21="Units",$C$21/$C$7,IF($E$21="Occupancy",$C$21*E54/SUM($E$44:$E$54),$C$21/$C$7))),0) -> 0 | J54: =IFERROR(IF($E$22="SF",$C$22*D54/$C$8,IF($E$22="Units",$C$22/$C$7,IF($E$22="Occupancy",$C$22*E54/SUM($E$44:$E$54),$C$22/$C$7))),0) -> 0 | K54: =SUM(F54:J54) -> 0 | L54: =K54*12 -> 0
B55: TOTALS | D55: =SUM(D44:D54) -> 1634 | E55: =SUM(E44:E54) -> 22 | F55: =SUM(F44:F54) -> 0 | G55: =SUM(G44:G54) -> 0 | H55: =SUM(H44:H54) -> 0 | I55: =SUM(I44:I54) -> 0 | J55: =SUM(J44:J54) -> 0 | K55: =SUM(K44:K54) -> 0 | L55: =SUM(L44:L54) -> 0
B57: Allocation Check | F57: =IF(ABS(F55-C18)<0.01,"✓","✗") -> ✓ | G57: =IF(ABS(G55-C19)<0.01,"✓","✗") -> ✓ | H57: =IF(ABS(H55-C20)<0.01,"✓","✗") -> ✓ | I57: =IF(ABS(I55-C21)<0.01,"✓","✗") -> ✓ | J57: =IF(ABS(J55-C22)<0.01,"✓","✗") -> ✓ | K57: =IF(ABS(K55-C23)<0.01,"✓","✗") -> ✓

Sheet Equity Partner
B2: EQUITY PARTNER SUMMARY
B3: Investment Structure, Distributions & Returns Analysis
B5: INVESTMENT SUMMARY | E5: WATERFALL STRUCTURE
B6: Total Acquisition Cost | C6: =Model!D101 -> #REF! | E6: Preferred Return (Pref) | F6: =#REF! -> #REF! | G6: Annual hurdle rate
B7: (-) Total Debt | C7: =Model!D102 -> #REF!
B8: Required Equity | C8: =Model!D103 -> #REF! | E8: Pre-Pref Splits:
E9: LP Share | F9: =#REF! -> #REF!
B10: LP Equity Investment | C10: =Model!D104 -> #REF! | E10: GP Share | F10: =#REF! -> #REF!
B11: GP Equity Investment | C11: =Model!D105 -> #REF!
B12: LP Ownership % | E12: Post-Pref Splits:
B13: GP Ownership % | C13: =IFERROR(C11/C8,0) -> 0 | E13: LP Share | F13: =#REF! -> #REF!
E14: GP Promote | F14: =#REF! -> #REF!
B15: EXIT STRATEGY
B16: Exit Cap Rate | C16: =#REF! -> #REF! | E16: Gross Sale Price | F16: =IFERROR(C17/C16,0) -> 0
B17: Forward NOI at Exit | C17: =Model!F73 -> #REF! | E17: (-) Selling Costs | F17: =Model!D96
B18: Hold Period | C18: 5 | D18: Years | E18: (-) Loan Payoffs | F18: =Model!D97
E19: Net Sale Proceeds | F19: =IFERROR(F16-F17-F18,0) -> 0
B21: ANNUAL DISTRIBUTION WATERFALL
C22: Year 1 | D22: Year 2 | E22: Year 3 | F22: Year 4 | G22: Year 5 | H22: Exit | I22: Total
B23: Distributable Cash | C23: =#REF! -> #REF! | D23: =#REF! -> #REF! | E23: =#REF! -> #REF! | F23: =#REF! -> #REF! | G23: =#REF! -> #REF! | H23: =F19 -> 0 | I23: =SUM(C23:H23) -> #REF!
B25: LP Preferred Return | C25: =IFERROR($C$10*$F$6,0) -> 0 | D25: =IFERROR($C$10*$F$6,0) -> 0 | E25: =IFERROR($C$10*$F$6,0) -> 0 | F25: =IFERROR($C$10*$F$6,0) -> 0 | G25: =IFERROR($C$10*$F$6,0) -> 0 | I25: =SUM(C25:G25) -> 0
B26: LP Distribution | C26: =#REF! -> #REF! | D26: =#REF! -> #REF! | E26: =#REF! -> #REF! | F26: =#REF! -> #REF! | G26: =#REF! -> #REF! | H26: =IFERROR(H23*$F$13,0) -> 0 | I26: =SUM(C26:H26) -> #REF!
B27: GP Distribution | C27: =#REF! -> #REF! | D27: =#REF! -> #REF! | E27: =#REF! -> #REF! | F27: =#REF! -> #REF! | G27: =#REF! -> #REF! | H27: =IFERROR(H23*$F$14,0) -> 0 | I27: =SUM(C27:H27) -> #REF!
B29: Check (should = 0) | C29: =C23-C26-C27 -> #REF! | D29: =D23-D26-D27 -> #REF! | E29: =E23-E26-E27 -> #REF! | F29: =F23-F26-F27 -> #REF! | G29: =G23-G26-G27 -> #REF! | H29: =H23-H26-H27 -> 0 | I29: =I23-I26-I27 -> #REF!
B31: RETURN METRICS | G31: LP CASH FLOW SUMMARY
B32: Metric | C32: LP | D32: GP | E32: Total | G32: Item | H32: Amount
B33: Initial Investment | C33: =C10 -> #REF! | D33: =C11 -> #REF! | E33: =C8 -> #REF! | G33: Initial Investment | H33: =-C10 -> #REF! | I33: Cash Out
B34: Total Distributions | C34: =I26 -> #REF! | D34: =I27 -> #REF! | E34: =I23 -> #REF! | G34: Year 1 Distribution | H34: =C26 -> #REF! | I34: Cash In
B35: Net Profit | C35: =C34-C33 -> #REF! | D35: =D34-D33 -> #REF! | E35: =E34-E33 -> #REF! | G35: Year 2 Distribution | H35: =D26 -> #REF! | I35: Cash In
B36: Multiple on Invested Capital | C36: =IFERROR(C34/C33,0) -> 0 | D36: =IFERROR(D34/D33,0) -> 0 | E36: =IFERROR(E34/E33,0) -> 0 | G36: Year 3 Distribution | H36: =E26 -> #REF! | I36: Cash In
B37: Cash-on-Cash (Year 1) | C37: =IFERROR(C26/C33,0) -> 0 | D37: =IFERROR(C27/D33,0) -> 0 | E37: =IFERROR(C23/E33,0) -> 0 | G37: Year 4 Distribution | H37: =F26 -> #REF! | I37: Cash In
G38: Year 5 Distribution | H38: =G26 -> #REF! | I38: Cash In
B39: IRR (5-Yr Exit) | C39: =Model!C114 | D39: =Model!D114 | E39: =Model!E114 | G39: Exit Proceeds (LP Share) | H39: =H26 -> 0 | I39: Cash In
G40: Net Cash Position | H40: =SUM(H33:H39) -> #REF!
B42: COLOR LEGEND: | D42: Note: This sheet pulls data from Model sheet. Errors will resolve when Model data is populated.
B43: Green text = Linked from Model sheet
B44: Blue text = User input
B45: Black text = Calculated formula

Sheet OM DATA PARSING MAP
B2: OM DATA PARSING MAP
B3: Map incoming Offering Memorandum data to underwriting model cells
B5: INSTRUCTIONS
B6: 1. Paste OM data in Column C (Source Value)
B7: 2. Values automatically map to the Model sheet via formulas
B8: 3. Yellow cells = required inputs, Gray cells = optional
B10: OM Field Name | C10: Source Value (Paste Here) | D10: Data Type | E10: Maps To Cell | F10: Model Section | G10: Notes
B12: PROPERTY INFORMATION
B13: Property Name | D13: Text | E13: Model!D6 | F13: Key Metrics
B14: Property Address | D14: Text | E14: Model!D7 (note) | F14: Key Metrics | G14: Store in note or separate field
B15: Total Units | D15: Number | E15: Model!D7 | F15: Key Metrics | G15: Required
B16: Total Square Feet | D16: Number | E16: Model!D8 | F16: Key Metrics | G16: Building SF
B17: Year Built | D17: Number | E17: Model!D22 | F17: Assumptions
B18: Lot Size (Acres) | D18: Number | E18: - | F18: Reference | G18: Not mapped - for reference
B19: Zoning | D19: Text | E19: - | F19: Reference | G19: Not mapped - for reference
B20: Parking Spaces | D20: Number | E20: - | F20: Reference
B22: ACQUISITION / PRICING
B23: Asking Price | D23: Currency | E23: Model!D9 | F23: Key Metrics | G23: Purchase Price input
B24: Price Per Unit | D24: Currency | E24: - | F24: Calculated | G24: Auto-calculated from Price/Units
B25: Price Per SF | D25: Currency | E25: - | F25: Calculated | G25: Auto-calculated
B26: Current Cap Rate | D26: Percent | E26: - | F26: Reference | G26: Seller's stated cap
B27: Pro Forma Cap Rate | D27: Percent | E27: - | F27: Reference | G27: Seller's pro forma
B28: Closing Costs | D28: Currency | E28: Model!D23 | F28: Assumptions | G28: Estimate if not provided
B29: Due Diligence Budget | D29: Currency | E29: Model!D24 | F29: Assumptions
B30: CapEx Budget | D30: Currency | E30: Model!D25 | F30: Assumptions | G30: Renovation/deferred maint
B32: INCOME (T-12 or Pro Forma)
B33: Gross Potential Rent (Annual) | D33: Currency | E33: Model!D63 | F33: Revenue | G33: GPR from OM
B34: Vacancy Loss % | D34: Percent | E34: Model!H22 | F34: Assumptions | G34: Economic vacancy rate
B35: Loss to Lease (Annual) | D35: Currency | E35: Model!D65 | F35: Revenue | G35: Below-market leases
B36: Concessions (Annual) | D36: Currency | E36: - | F36: Reference | G36: Use % in Model!H24
B37: Bad Debt % | D37: Percent | E37: Model!H23 | F37: Assumptions
B38: Laundry Income | D38: Currency | E38: Model!C71 | F38: Revenue | G38: $/unit/month
B39: Parking Income | D39: Currency | E39: Model!C72 | F39: Revenue | G39: $/unit/month
B40: Pet Income | D40: Currency | E40: Model!C73 | F40: Revenue | G40: $/unit/month
B41: Other Income | D41: Currency | E41: Model!C74-C76 | F41: Revenue | G41: Split across line items
B42: RUBS/Utility Reimbursement | D42: Currency | E42: Model!C81-C84 | F42: Revenue | G42: If tenant-paid utilities
B44: OPERATING EXPENSES (T-12 or Pro Forma)
B45: Real Estate Taxes | D45: Currency | E45: Model!C93 | F45: Expenses | G45: Annual or $/unit/mo
B46: Property Insurance | D46: Currency | E46: Model!C94 | F46: Expenses | G46: Annual or $/unit/mo
B47: Water/Sewer | D47: Currency | E47: Model!C95 | F47: Expenses | G47: If owner-paid
B48: Electric (Common Area) | D48: Currency | E48: Model!C96 | F48: Expenses
B49: Gas | D49: Currency | E49: Model!C97 | F49: Expenses | G49: If owner-paid
B50: Trash Removal | D50: Currency | E50: Model!C98 | F50: Expenses | G50: If owner-paid
B51: Repairs & Maintenance | D51: Currency | E51: Model!C99 | F51: Expenses
B52: Landscaping | D52: Currency | E52: Model!C100 | F52: Expenses
B53: Pest Control | D53: Currency | E53: Model!C101 | F53: Expenses
B54: Snow Removal | D54: Currency | E54: Model!C102 | F54: Expenses | G54: If applicable
B55: Unit Turnover/Make Ready | D55: Currency | E55: Model!C103 | F55: Expenses
B56: Management Fee % | D56: Percent | E56: Model!H25 | F56: Assumptions | G56: % of EGI
B57: On-Site Payroll | D57: Currency | E57: Model!C105 | F57: Expenses | G57: If applicable
B58: Marketing/Advertising | D58: Currency | E58: Model!C106 | F58: Expenses
B59: Legal & Professional | D59: Currency | E59: Model!C107 | F59: Expenses
B60: Accounting | D60: Currency | E60: Model!C108 | F60: Expenses
B61: Administrative/G&A | D61: Currency | E61: Model!C109 | F61: Expenses
B62: Security | D62: Currency | E62: Model!C110 | F62: Expenses
B63: Cable/Internet | D63: Currency | E63: Model!C111 | F63: Expenses
B64: Total Operating Expenses | D64: Currency | E64: - | F64: Calculated | G64: Sum of above - verify
B65: NOI (from OM) | D65: Currency | E65: - | F65: Reference | G65: Compare to model output
B67: RENT ROLL DATA
B68: Unit Numbers | D68: Text | E68: Model!B33:B56 | F68: Rent Roll | G68: List of unit IDs
B69: Unit Types (1BR, 2BR, etc) | D69: Text | E69: Model!C33:C56 | F69: Rent Roll | G69: Bedroom/bath config
B70: Unit Square Feet | D70: Number | E70: Model!D33:D56 | F70: Rent Roll | G70: Per unit
B71: Unit Status | D71: Text | E71: Model!E33:E56 | F71: Rent Roll | G71: Renovated/Classic/Vacant
B72: Market Rent | D72: Currency | E72: Model!F33:F56 | F72: Rent Roll | G72: Current market rate
B73: In-Place Rent | D73: Currency | E73: Model!G33:G56 | F73: Rent Roll | G73: Actual rent collected
B74: Lease Start Date | D74: Date | E74: Model!I33:I56 | F74: Rent Roll
B75: Lease End Date | D75: Date | E75: Model!J33:J56 | F75: Rent Roll
B76: Tenant Name | D76: Text | E76: Model!K33:K56 | F76: Rent Roll | G76: Or 'Vacant'
B78: EXISTING FINANCING (for Subject-To)
B79: Existing Loan Balance | D79: Currency | E79: Model!D127 | F79: Financing | G79: If assuming existing debt
B80: Existing Loan Rate | D80: Percent | E80: Model!D128 | F80: Financing | G80: Current interest rate
B81: Remaining Term (Months) | D81: Number | E81: Model!D129 | F81: Financing | G81: Months remaining
B82: Monthly P&I Payment | D82: Currency | E82: - | F82: Calculated | G82: Verify against model
B83: Loan Maturity Date | D83: Date | E83: - | F83: Reference | G83: Calculate from term
B84: Prepayment Penalty | D84: Text | E84: - | F84: Reference | G84: Note any restrictions
B85: Assumable (Y/N) | D85: Text | E85: - | F85: Reference | G85: Key for subject-to
B87: GROWTH ASSUMPTIONS (Your Inputs)
B88: Annual Rent Growth % | D88: Percent | E88: Model!H20 | F88: Assumptions | G88: Market rent escalation
B89: Annual Expense Growth % | D89: Percent | E89: Model!H21 | F89: Assumptions | G89: Inflation factor
B90: Exit Cap Rate (5-Year) | D90: Percent | E90: Model!H26 | F90: Assumptions | G90: For reversion calc
B91: Exit Cap Rate (10-Year) | D91: Percent | E91: Model!H27 | F91: Assumptions | G91: For reversion calc
B92: Selling Costs % | D92: Percent | E92: Model!L20 | F92: Assumptions | G92: Broker fees, transfer tax
B93: CapEx Reserve $/Unit/Year | D93: Currency | E93: Model!L21 | F93: Assumptions | G93: Ongoing reserves
B96: QUICK REFERENCE - KEY MODEL CELLS
B97: Output | C97: Cell | D97: Output | E97: Cell
B98: Purchase Price | C98: Model!D9 | D98: Total Units | E98: Model!D7
B99: Year 1 NOI | C99: Model!E117 | D99: Year 1 EGI | E99: Model!E87
B100: Going-In Cap Rate | C100: Model!D13 | D100: Stabilized Cap Rate | E100: Model!D14
B101: Total Debt | C101: Model!D164 | D101: Required Equity | E101: Model!D197
B102: Project IRR (5-Yr) | C102: Model!O230 | D102: Project IRR (10-Yr) | E102: Model!P230
B103: LP IRR (5-Yr) | C103: Model!O231 | D103: LP IRR (10-Yr) | E103: Model!P231
B104: RUBS Toggle | C104: Model!D80 | D104: 1=Tenant, 0=Owner | E104: -
B107: LEGEND
B108: Yellow cells | C108: Required inputs
B109: Gray cells | C109: Optional inputs
B110: Green cells | C110: Your assumptions (not from OM)
B111: Blue text | C111: Cell references in Model sheet
B114: RUBS SHEET MAPPING
B115: Configuration
B116: Total Units (linked) | D116: Number | E116: RUBS!C7 | F116: Config | G116: Links to Model!D7
...
